{
	"credit": "By.Green_Chennai",
	"textures": {
		"2": "Desktop/crystal",
		"particle": "Desktop/crystal"
	},
	"elements": [
		{
			"name": "voxel",
			"from": [7.5, 1.89189, 6.48649],
			"to": [8.5, 12.89189, 9.48649],
			"rotation": {"angle": 0, "axis": "y", "origin": [8.5, 7.89189, 8.48649]},
			"faces": {
				"north": {"uv": [0.25, 0.25, 0.75, 0.75], "texture": "#2"},
				"east": {"uv": [0.25, 0.25, 0.75, 0.75], "texture": "#2"},
				"south": {"uv": [0.25, 0.25, 0.75, 0.75], "texture": "#2"},
				"west": {"uv": [0.25, 0.25, 0.75, 0.75], "texture": "#2"},
				"up": {"uv": [0.25, 0.25, 0.75, 0.75], "texture": "#2"},
				"down": {"uv": [0.25, 0.25, 0.75, 0.75], "texture": "#2"}
			}
		},
		{
			"name": "voxel",
			"from": [8.5, 2.89189, 6.48649],
			"to": [9.5, 11.89189, 9.48649],
			"rotation": {"angle": 0, "axis": "y", "origin": [8.5, 7.89189, 8.48649]},
			"faces": {
				"north": {"uv": [0.25, 0.25, 0.75, 0.75], "texture": "#2"},
				"east": {"uv": [0.25, 0.25, 0.75, 0.75], "texture": "#2"},
				"south": {"uv": [0.25, 0.25, 0.75, 0.75], "texture": "#2"},
				"west": {"uv": [0.25, 0.25, 0.75, 0.75], "texture": "#2"},
				"up": {"uv": [0.25, 0.25, 0.75, 0.75], "texture": "#2"},
				"down": {"uv": [0.25, 0.25, 0.75, 0.75], "texture": "#2"}
			}
		},
		{
			"name": "voxel",
			"from": [6.5, 2.89189, 6.48649],
			"to": [7.5, 11.89189, 9.48649],
			"rotation": {"angle": 0, "axis": "y", "origin": [8.5, 7.89189, 8.48649]},
			"faces": {
				"north": {"uv": [0.25, 0.25, 0.75, 0.75], "texture": "#2"},
				"east": {"uv": [0.25, 0.25, 0.75, 0.75], "texture": "#2"},
				"south": {"uv": [0.25, 0.25, 0.75, 0.75], "texture": "#2"},
				"west": {"uv": [0.25, 0.25, 0.75, 0.75], "texture": "#2"},
				"up": {"uv": [0.25, 0.25, 0.75, 0.75], "texture": "#2"},
				"down": {"uv": [0.25, 0.25, 0.75, 0.75], "texture": "#2"}
			}
		},
		{
			"name": "voxel",
			"from": [9.5, 3.89189, 6.48649],
			"to": [10.5, 10.89189, 9.48649],
			"rotation": {"angle": 0, "axis": "y", "origin": [8.5, 7.89189, 8.48649]},
			"faces": {
				"north": {"uv": [0.25, 0.25, 0.75, 0.75], "texture": "#2"},
				"east": {"uv": [0.25, 0.25, 0.75, 0.75], "texture": "#2"},
				"south": {"uv": [0.25, 0.25, 0.75, 0.75], "texture": "#2"},
				"west": {"uv": [0.25, 0.25, 0.75, 0.75], "texture": "#2"},
				"up": {"uv": [0.25, 0.25, 0.75, 0.75], "texture": "#2"},
				"down": {"uv": [0.25, 0.25, 0.75, 0.75], "texture": "#2"}
			}
		},
		{
			"name": "voxel",
			"from": [5.5, 5.89189, 9.48649],
			"to": [10.5, 8.89189, 10.48649],
			"rotation": {"angle": 0, "axis": "y", "origin": [8.5, 7.89189, 8.48649]},
			"faces": {
				"north": {"uv": [0.25, 0.25, 0.75, 0.75], "texture": "#2"},
				"east": {"uv": [0.25, 0.25, 0.75, 0.75], "texture": "#2"},
				"south": {"uv": [0.25, 0.25, 0.75, 0.75], "texture": "#2"},
				"west": {"uv": [0.25, 0.25, 0.75, 0.75], "texture": "#2"},
				"up": {"uv": [0.25, 0.25, 0.75, 0.75], "texture": "#2"},
				"down": {"uv": [0.25, 0.25, 0.75, 0.75], "texture": "#2"}
			}
		},
		{
			"name": "voxel",
			"from": [6.5, 4.89189, 10.48649],
			"to": [9.5, 9.89189, 11.48649],
			"rotation": {"angle": 0, "axis": "y", "origin": [8.5, 7.89189, 8.48649]},
			"faces": {
				"north": {"uv": [0.25, 0.25, 0.75, 0.75], "texture": "#2"},
				"east": {"uv": [0.25, 0.25, 0.75, 0.75], "texture": "#2"},
				"south": {"uv": [0.25, 0.25, 0.75, 0.75], "texture": "#2"},
				"west": {"uv": [0.25, 0.25, 0.75, 0.75], "texture": "#2"},
				"up": {"uv": [0.25, 0.25, 0.75, 0.75], "texture": "#2"},
				"down": {"uv": [0.25, 0.25, 0.75, 0.75], "texture": "#2"}
			}
		},
		{
			"name": "voxel",
			"from": [5.5, 3.89189, 6.48649],
			"to": [6.5, 10.89189, 9.48649],
			"rotation": {"angle": 0, "axis": "y", "origin": [8.5, 7.89189, 8.48649]},
			"faces": {
				"north": {"uv": [0.25, 0.25, 0.75, 0.75], "texture": "#2"},
				"east": {"uv": [0.25, 0.25, 0.75, 0.75], "texture": "#2"},
				"south": {"uv": [0.25, 0.25, 0.75, 0.75], "texture": "#2"},
				"west": {"uv": [0.25, 0.25, 0.75, 0.75], "texture": "#2"},
				"up": {"uv": [0.25, 0.25, 0.75, 0.75], "texture": "#2"},
				"down": {"uv": [0.25, 0.25, 0.75, 0.75], "texture": "#2"}
			}
		},
		{
			"name": "voxel",
			"from": [7.5, 9.89189, 9.48649],
			"to": [8.5, 10.89189, 11.48649],
			"rotation": {"angle": 0, "axis": "y", "origin": [8.5, 7.89189, 8.48649]},
			"faces": {
				"north": {"uv": [0.25, 0.25, 0.75, 0.75], "texture": "#2"},
				"east": {"uv": [0.25, 0.25, 0.75, 0.75], "texture": "#2"},
				"south": {"uv": [0.25, 0.25, 0.75, 0.75], "texture": "#2"},
				"west": {"uv": [0.25, 0.25, 0.75, 0.75], "texture": "#2"},
				"up": {"uv": [0.25, 0.25, 0.75, 0.75], "texture": "#2"},
				"down": {"uv": [0.25, 0.25, 0.75, 0.75], "texture": "#2"}
			}
		},
		{
			"name": "voxel",
			"from": [7.5, 10.89189, 9.48649],
			"to": [8.5, 11.89189, 10.48649],
			"rotation": {"angle": 0, "axis": "y", "origin": [8.5, 7.89189, 8.48649]},
			"faces": {
				"north": {"uv": [0.25, 0.25, 0.75, 0.75], "texture": "#2"},
				"east": {"uv": [0.25, 0.25, 0.75, 0.75], "texture": "#2"},
				"south": {"uv": [0.25, 0.25, 0.75, 0.75], "texture": "#2"},
				"west": {"uv": [0.25, 0.25, 0.75, 0.75], "texture": "#2"},
				"up": {"uv": [0.25, 0.25, 0.75, 0.75], "texture": "#2"},
				"down": {"uv": [0.25, 0.25, 0.75, 0.75], "texture": "#2"}
			}
		},
		{
			"name": "voxel",
			"from": [10.5, 4.89189, 6.48649],
			"to": [11.5, 9.89189, 9.48649],
			"rotation": {"angle": 0, "axis": "y", "origin": [8.5, 7.89189, 8.48649]},
			"faces": {
				"north": {"uv": [0.25, 0.25, 0.75, 0.75], "texture": "#2"},
				"east": {"uv": [0.25, 0.25, 0.75, 0.75], "texture": "#2"},
				"south": {"uv": [0.25, 0.25, 0.75, 0.75], "texture": "#2"},
				"west": {"uv": [0.25, 0.25, 0.75, 0.75], "texture": "#2"},
				"up": {"uv": [0.25, 0.25, 0.75, 0.75], "texture": "#2"},
				"down": {"uv": [0.25, 0.25, 0.75, 0.75], "texture": "#2"}
			}
		},
		{
			"name": "voxel",
			"from": [4.5, 4.89189, 6.48649],
			"to": [5.5, 9.89189, 9.48649],
			"rotation": {"angle": 0, "axis": "y", "origin": [8.5, 7.89189, 8.48649]},
			"faces": {
				"north": {"uv": [0.25, 0.25, 0.75, 0.75], "texture": "#2"},
				"east": {"uv": [0.25, 0.25, 0.75, 0.75], "texture": "#2"},
				"south": {"uv": [0.25, 0.25, 0.75, 0.75], "texture": "#2"},
				"west": {"uv": [0.25, 0.25, 0.75, 0.75], "texture": "#2"},
				"up": {"uv": [0.25, 0.25, 0.75, 0.75], "texture": "#2"},
				"down": {"uv": [0.25, 0.25, 0.75, 0.75], "texture": "#2"}
			}
		},
		{
			"name": "voxel",
			"from": [6.5, 8.89189, 9.48649],
			"to": [9.5, 9.89189, 10.48649],
			"rotation": {"angle": 0, "axis": "y", "origin": [8.5, 7.89189, 8.48649]},
			"faces": {
				"north": {"uv": [0.25, 0.25, 0.75, 0.75], "texture": "#2"},
				"east": {"uv": [0.25, 0.25, 0.75, 0.75], "texture": "#2"},
				"south": {"uv": [0.25, 0.25, 0.75, 0.75], "texture": "#2"},
				"west": {"uv": [0.25, 0.25, 0.75, 0.75], "texture": "#2"},
				"up": {"uv": [0.25, 0.25, 0.75, 0.75], "texture": "#2"},
				"down": {"uv": [0.25, 0.25, 0.75, 0.75], "texture": "#2"}
			}
		},
		{
			"name": "voxel",
			"from": [8.5, 9.89189, 9.48649],
			"to": [9.5, 10.89189, 10.48649],
			"rotation": {"angle": 0, "axis": "y", "origin": [8.5, 7.89189, 8.48649]},
			"faces": {
				"north": {"uv": [0.25, 0.25, 0.75, 0.75], "texture": "#2"},
				"east": {"uv": [0.25, 0.25, 0.75, 0.75], "texture": "#2"},
				"south": {"uv": [0.25, 0.25, 0.75, 0.75], "texture": "#2"},
				"west": {"uv": [0.25, 0.25, 0.75, 0.75], "texture": "#2"},
				"up": {"uv": [0.25, 0.25, 0.75, 0.75], "texture": "#2"},
				"down": {"uv": [0.25, 0.25, 0.75, 0.75], "texture": "#2"}
			}
		},
		{
			"name": "voxel",
			"from": [6.5, 3.89189, 9.48649],
			"to": [9.5, 5.89189, 10.48649],
			"rotation": {"angle": 0, "axis": "y", "origin": [8.5, 7.89189, 8.48649]},
			"faces": {
				"north": {"uv": [0.25, 0.25, 0.75, 0.75], "texture": "#2"},
				"east": {"uv": [0.25, 0.25, 0.75, 0.75], "texture": "#2"},
				"south": {"uv": [0.25, 0.25, 0.75, 0.75], "texture": "#2"},
				"west": {"uv": [0.25, 0.25, 0.75, 0.75], "texture": "#2"},
				"up": {"uv": [0.25, 0.25, 0.75, 0.75], "texture": "#2"},
				"down": {"uv": [0.25, 0.25, 0.75, 0.75], "texture": "#2"}
			}
		},
		{
			"name": "voxel",
			"from": [6.5, 9.89189, 9.48649],
			"to": [7.5, 10.89189, 10.48649],
			"rotation": {"angle": 0, "axis": "y", "origin": [8.5, 7.89189, 8.48649]},
			"faces": {
				"north": {"uv": [0.25, 0.25, 0.75, 0.75], "texture": "#2"},
				"east": {"uv": [0.25, 0.25, 0.75, 0.75], "texture": "#2"},
				"south": {"uv": [0.25, 0.25, 0.75, 0.75], "texture": "#2"},
				"west": {"uv": [0.25, 0.25, 0.75, 0.75], "texture": "#2"},
				"up": {"uv": [0.25, 0.25, 0.75, 0.75], "texture": "#2"},
				"down": {"uv": [0.25, 0.25, 0.75, 0.75], "texture": "#2"}
			}
		},
		{
			"name": "voxel",
			"from": [6.5, 1.89189, 7.48649],
			"to": [7.5, 2.89189, 8.48649],
			"rotation": {"angle": 0, "axis": "y", "origin": [8.5, 7.89189, 8.48649]},
			"faces": {
				"north": {"uv": [0.25, 0.25, 0.75, 0.75], "texture": "#2"},
				"east": {"uv": [0.25, 0.25, 0.75, 0.75], "texture": "#2"},
				"south": {"uv": [0.25, 0.25, 0.75, 0.75], "texture": "#2"},
				"west": {"uv": [0.25, 0.25, 0.75, 0.75], "texture": "#2"},
				"up": {"uv": [0.25, 0.25, 0.75, 0.75], "texture": "#2"},
				"down": {"uv": [0.25, 0.25, 0.75, 0.75], "texture": "#2"}
			}
		},
		{
			"name": "voxel",
			"from": [8.5, 1.89189, 7.48649],
			"to": [9.5, 2.89189, 8.48649],
			"rotation": {"angle": 0, "axis": "y", "origin": [8.5, 7.89189, 8.48649]},
			"faces": {
				"north": {"uv": [0.25, 0.25, 0.75, 0.75], "texture": "#2"},
				"east": {"uv": [0.25, 0.25, 0.75, 0.75], "texture": "#2"},
				"south": {"uv": [0.25, 0.25, 0.75, 0.75], "texture": "#2"},
				"west": {"uv": [0.25, 0.25, 0.75, 0.75], "texture": "#2"},
				"up": {"uv": [0.25, 0.25, 0.75, 0.75], "texture": "#2"},
				"down": {"uv": [0.25, 0.25, 0.75, 0.75], "texture": "#2"}
			}
		},
		{
			"name": "voxel",
			"from": [7.5, 0.89189, 7.48649],
			"to": [8.5, 1.89189, 8.48649],
			"rotation": {"angle": 0, "axis": "y", "origin": [8.5, 7.89189, 8.48649]},
			"faces": {
				"north": {"uv": [0.25, 0.25, 0.75, 0.75], "texture": "#2"},
				"east": {"uv": [0.25, 0.25, 0.75, 0.75], "texture": "#2"},
				"south": {"uv": [0.25, 0.25, 0.75, 0.75], "texture": "#2"},
				"west": {"uv": [0.25, 0.25, 0.75, 0.75], "texture": "#2"},
				"up": {"uv": [0.25, 0.25, 0.75, 0.75], "texture": "#2"},
				"down": {"uv": [0.25, 0.25, 0.75, 0.75], "texture": "#2"}
			}
		},
		{
			"name": "voxel",
			"from": [9.5, 2.89189, 7.48649],
			"to": [10.5, 3.89189, 8.48649],
			"rotation": {"angle": 0, "axis": "y", "origin": [8.5, 7.89189, 8.48649]},
			"faces": {
				"north": {"uv": [0.25, 0.25, 0.75, 0.75], "texture": "#2"},
				"east": {"uv": [0.25, 0.25, 0.75, 0.75], "texture": "#2"},
				"south": {"uv": [0.25, 0.25, 0.75, 0.75], "texture": "#2"},
				"west": {"uv": [0.25, 0.25, 0.75, 0.75], "texture": "#2"},
				"up": {"uv": [0.25, 0.25, 0.75, 0.75], "texture": "#2"},
				"down": {"uv": [0.25, 0.25, 0.75, 0.75], "texture": "#2"}
			}
		},
		{
			"name": "voxel",
			"from": [5.5, 2.89189, 7.48649],
			"to": [6.5, 3.89189, 8.48649],
			"rotation": {"angle": 0, "axis": "y", "origin": [8.5, 7.89189, 8.48649]},
			"faces": {
				"north": {"uv": [0.25, 0.25, 0.75, 0.75], "texture": "#2"},
				"east": {"uv": [0.25, 0.25, 0.75, 0.75], "texture": "#2"},
				"south": {"uv": [0.25, 0.25, 0.75, 0.75], "texture": "#2"},
				"west": {"uv": [0.25, 0.25, 0.75, 0.75], "texture": "#2"},
				"up": {"uv": [0.25, 0.25, 0.75, 0.75], "texture": "#2"},
				"down": {"uv": [0.25, 0.25, 0.75, 0.75], "texture": "#2"}
			}
		},
		{
			"name": "voxel",
			"from": [4.5, 3.89189, 7.48649],
			"to": [5.5, 4.89189, 8.48649],
			"rotation": {"angle": 0, "axis": "y", "origin": [8.5, 7.89189, 8.48649]},
			"faces": {
				"north": {"uv": [0.25, 0.25, 0.75, 0.75], "texture": "#2"},
				"east": {"uv": [0.25, 0.25, 0.75, 0.75], "texture": "#2"},
				"south": {"uv": [0.25, 0.25, 0.75, 0.75], "texture": "#2"},
				"west": {"uv": [0.25, 0.25, 0.75, 0.75], "texture": "#2"},
				"up": {"uv": [0.25, 0.25, 0.75, 0.75], "texture": "#2"},
				"down": {"uv": [0.25, 0.25, 0.75, 0.75], "texture": "#2"}
			}
		},
		{
			"name": "voxel",
			"from": [6.5, 4.89189, 4.48649],
			"to": [9.5, 9.89189, 6.48649],
			"rotation": {"angle": 0, "axis": "y", "origin": [8.5, 7.89189, 8.48649]},
			"faces": {
				"north": {"uv": [0.25, 0.25, 0.75, 0.75], "texture": "#2"},
				"east": {"uv": [0.25, 0.25, 0.75, 0.75], "texture": "#2"},
				"south": {"uv": [0.25, 0.25, 0.75, 0.75], "texture": "#2"},
				"west": {"uv": [0.25, 0.25, 0.75, 0.75], "texture": "#2"},
				"up": {"uv": [0.25, 0.25, 0.75, 0.75], "texture": "#2"},
				"down": {"uv": [0.25, 0.25, 0.75, 0.75], "texture": "#2"}
			}
		},
		{
			"name": "voxel",
			"from": [7.5, 9.89189, 4.48649],
			"to": [8.5, 10.89189, 6.48649],
			"rotation": {"angle": 0, "axis": "y", "origin": [8.5, 7.89189, 8.48649]},
			"faces": {
				"north": {"uv": [0.25, 0.25, 0.75, 0.75], "texture": "#2"},
				"east": {"uv": [0.25, 0.25, 0.75, 0.75], "texture": "#2"},
				"south": {"uv": [0.25, 0.25, 0.75, 0.75], "texture": "#2"},
				"west": {"uv": [0.25, 0.25, 0.75, 0.75], "texture": "#2"},
				"up": {"uv": [0.25, 0.25, 0.75, 0.75], "texture": "#2"},
				"down": {"uv": [0.25, 0.25, 0.75, 0.75], "texture": "#2"}
			}
		},
		{
			"name": "voxel",
			"from": [4.5, 9.89189, 7.48649],
			"to": [5.5, 10.89189, 8.48649],
			"rotation": {"angle": 0, "axis": "y", "origin": [8.5, 7.89189, 8.48649]},
			"faces": {
				"north": {"uv": [0.25, 0.25, 0.75, 0.75], "texture": "#2"},
				"east": {"uv": [0.25, 0.25, 0.75, 0.75], "texture": "#2"},
				"south": {"uv": [0.25, 0.25, 0.75, 0.75], "texture": "#2"},
				"west": {"uv": [0.25, 0.25, 0.75, 0.75], "texture": "#2"},
				"up": {"uv": [0.25, 0.25, 0.75, 0.75], "texture": "#2"},
				"down": {"uv": [0.25, 0.25, 0.75, 0.75], "texture": "#2"}
			}
		},
		{
			"name": "voxel",
			"from": [5.5, 10.89189, 7.48649],
			"to": [6.5, 11.89189, 8.48649],
			"rotation": {"angle": 0, "axis": "y", "origin": [8.5, 7.89189, 8.48649]},
			"faces": {
				"north": {"uv": [0.25, 0.25, 0.75, 0.75], "texture": "#2"},
				"east": {"uv": [0.25, 0.25, 0.75, 0.75], "texture": "#2"},
				"south": {"uv": [0.25, 0.25, 0.75, 0.75], "texture": "#2"},
				"west": {"uv": [0.25, 0.25, 0.75, 0.75], "texture": "#2"},
				"up": {"uv": [0.25, 0.25, 0.75, 0.75], "texture": "#2"},
				"down": {"uv": [0.25, 0.25, 0.75, 0.75], "texture": "#2"}
			}
		},
		{
			"name": "voxel",
			"from": [5.5, 5.89189, 5.48649],
			"to": [6.5, 8.89189, 6.48649],
			"rotation": {"angle": 0, "axis": "y", "origin": [8.5, 7.89189, 8.48649]},
			"faces": {
				"north": {"uv": [0.25, 0.25, 0.75, 0.75], "texture": "#2"},
				"east": {"uv": [0.25, 0.25, 0.75, 0.75], "texture": "#2"},
				"south": {"uv": [0.25, 0.25, 0.75, 0.75], "texture": "#2"},
				"west": {"uv": [0.25, 0.25, 0.75, 0.75], "texture": "#2"},
				"up": {"uv": [0.25, 0.25, 0.75, 0.75], "texture": "#2"},
				"down": {"uv": [0.25, 0.25, 0.75, 0.75], "texture": "#2"}
			}
		},
		{
			"name": "voxel",
			"from": [6.5, 3.89189, 5.48649],
			"to": [9.5, 4.89189, 6.48649],
			"rotation": {"angle": 0, "axis": "y", "origin": [8.5, 7.89189, 8.48649]},
			"faces": {
				"north": {"uv": [0.25, 0.25, 0.75, 0.75], "texture": "#2"},
				"east": {"uv": [0.25, 0.25, 0.75, 0.75], "texture": "#2"},
				"south": {"uv": [0.25, 0.25, 0.75, 0.75], "texture": "#2"},
				"west": {"uv": [0.25, 0.25, 0.75, 0.75], "texture": "#2"},
				"up": {"uv": [0.25, 0.25, 0.75, 0.75], "texture": "#2"},
				"down": {"uv": [0.25, 0.25, 0.75, 0.75], "texture": "#2"}
			}
		},
		{
			"name": "voxel",
			"from": [10.5, 3.89189, 7.48649],
			"to": [11.5, 4.89189, 8.48649],
			"rotation": {"angle": 0, "axis": "y", "origin": [8.5, 7.89189, 8.48649]},
			"faces": {
				"north": {"uv": [0.25, 0.25, 0.75, 0.75], "texture": "#2"},
				"east": {"uv": [0.25, 0.25, 0.75, 0.75], "texture": "#2"},
				"south": {"uv": [0.25, 0.25, 0.75, 0.75], "texture": "#2"},
				"west": {"uv": [0.25, 0.25, 0.75, 0.75], "texture": "#2"},
				"up": {"uv": [0.25, 0.25, 0.75, 0.75], "texture": "#2"},
				"down": {"uv": [0.25, 0.25, 0.75, 0.75], "texture": "#2"}
			}
		},
		{
			"name": "voxel",
			"from": [9.5, 5.89189, 5.48649],
			"to": [10.5, 8.89189, 6.48649],
			"rotation": {"angle": 0, "axis": "y", "origin": [8.5, 7.89189, 8.48649]},
			"faces": {
				"north": {"uv": [0.25, 0.25, 0.75, 0.75], "texture": "#2"},
				"east": {"uv": [0.25, 0.25, 0.75, 0.75], "texture": "#2"},
				"south": {"uv": [0.25, 0.25, 0.75, 0.75], "texture": "#2"},
				"west": {"uv": [0.25, 0.25, 0.75, 0.75], "texture": "#2"},
				"up": {"uv": [0.25, 0.25, 0.75, 0.75], "texture": "#2"},
				"down": {"uv": [0.25, 0.25, 0.75, 0.75], "texture": "#2"}
			}
		},
		{
			"name": "voxel",
			"from": [6.5, 9.89189, 5.48649],
			"to": [7.5, 10.89189, 6.48649],
			"rotation": {"angle": 0, "axis": "y", "origin": [8.5, 7.89189, 8.48649]},
			"faces": {
				"north": {"uv": [0.25, 0.25, 0.75, 0.75], "texture": "#2"},
				"east": {"uv": [0.25, 0.25, 0.75, 0.75], "texture": "#2"},
				"south": {"uv": [0.25, 0.25, 0.75, 0.75], "texture": "#2"},
				"west": {"uv": [0.25, 0.25, 0.75, 0.75], "texture": "#2"},
				"up": {"uv": [0.25, 0.25, 0.75, 0.75], "texture": "#2"},
				"down": {"uv": [0.25, 0.25, 0.75, 0.75], "texture": "#2"}
			}
		},
		{
			"name": "voxel",
			"from": [8.5, 9.89189, 5.48649],
			"to": [9.5, 10.89189, 6.48649],
			"rotation": {"angle": 0, "axis": "y", "origin": [8.5, 7.89189, 8.48649]},
			"faces": {
				"north": {"uv": [0.25, 0.25, 0.75, 0.75], "texture": "#2"},
				"east": {"uv": [0.25, 0.25, 0.75, 0.75], "texture": "#2"},
				"south": {"uv": [0.25, 0.25, 0.75, 0.75], "texture": "#2"},
				"west": {"uv": [0.25, 0.25, 0.75, 0.75], "texture": "#2"},
				"up": {"uv": [0.25, 0.25, 0.75, 0.75], "texture": "#2"},
				"down": {"uv": [0.25, 0.25, 0.75, 0.75], "texture": "#2"}
			}
		},
		{
			"name": "voxel",
			"from": [10.5, 9.89189, 7.48649],
			"to": [11.5, 10.89189, 8.48649],
			"rotation": {"angle": 0, "axis": "y", "origin": [8.5, 7.89189, 8.48649]},
			"faces": {
				"north": {"uv": [0.25, 0.25, 0.75, 0.75], "texture": "#2"},
				"east": {"uv": [0.25, 0.25, 0.75, 0.75], "texture": "#2"},
				"south": {"uv": [0.25, 0.25, 0.75, 0.75], "texture": "#2"},
				"west": {"uv": [0.25, 0.25, 0.75, 0.75], "texture": "#2"},
				"up": {"uv": [0.25, 0.25, 0.75, 0.75], "texture": "#2"},
				"down": {"uv": [0.25, 0.25, 0.75, 0.75], "texture": "#2"}
			}
		},
		{
			"name": "voxel",
			"from": [7.5, 10.89189, 5.48649],
			"to": [8.5, 11.89189, 6.48649],
			"rotation": {"angle": 0, "axis": "y", "origin": [8.5, 7.89189, 8.48649]},
			"faces": {
				"north": {"uv": [0.25, 0.25, 0.75, 0.75], "texture": "#2"},
				"east": {"uv": [0.25, 0.25, 0.75, 0.75], "texture": "#2"},
				"south": {"uv": [0.25, 0.25, 0.75, 0.75], "texture": "#2"},
				"west": {"uv": [0.25, 0.25, 0.75, 0.75], "texture": "#2"},
				"up": {"uv": [0.25, 0.25, 0.75, 0.75], "texture": "#2"},
				"down": {"uv": [0.25, 0.25, 0.75, 0.75], "texture": "#2"}
			}
		},
		{
			"name": "voxel",
			"from": [9.5, 10.89189, 7.48649],
			"to": [10.5, 11.89189, 8.48649],
			"rotation": {"angle": 0, "axis": "y", "origin": [8.5, 7.89189, 8.48649]},
			"faces": {
				"north": {"uv": [0.25, 0.25, 0.75, 0.75], "texture": "#2"},
				"east": {"uv": [0.25, 0.25, 0.75, 0.75], "texture": "#2"},
				"south": {"uv": [0.25, 0.25, 0.75, 0.75], "texture": "#2"},
				"west": {"uv": [0.25, 0.25, 0.75, 0.75], "texture": "#2"},
				"up": {"uv": [0.25, 0.25, 0.75, 0.75], "texture": "#2"},
				"down": {"uv": [0.25, 0.25, 0.75, 0.75], "texture": "#2"}
			}
		},
		{
			"name": "voxel",
			"from": [6.5, 11.89189, 7.48649],
			"to": [7.5, 12.89189, 8.48649],
			"rotation": {"angle": 0, "axis": "y", "origin": [8.5, 7.89189, 8.48649]},
			"faces": {
				"north": {"uv": [0.25, 0.25, 0.75, 0.75], "texture": "#2"},
				"east": {"uv": [0.25, 0.25, 0.75, 0.75], "texture": "#2"},
				"south": {"uv": [0.25, 0.25, 0.75, 0.75], "texture": "#2"},
				"west": {"uv": [0.25, 0.25, 0.75, 0.75], "texture": "#2"},
				"up": {"uv": [0.25, 0.25, 0.75, 0.75], "texture": "#2"},
				"down": {"uv": [0.25, 0.25, 0.75, 0.75], "texture": "#2"}
			}
		},
		{
			"name": "voxel",
			"from": [8.5, 11.89189, 7.48649],
			"to": [9.5, 12.89189, 8.48649],
			"rotation": {"angle": 0, "axis": "y", "origin": [8.5, 7.89189, 8.48649]},
			"faces": {
				"north": {"uv": [0.25, 0.25, 0.75, 0.75], "texture": "#2"},
				"east": {"uv": [0.25, 0.25, 0.75, 0.75], "texture": "#2"},
				"south": {"uv": [0.25, 0.25, 0.75, 0.75], "texture": "#2"},
				"west": {"uv": [0.25, 0.25, 0.75, 0.75], "texture": "#2"},
				"up": {"uv": [0.25, 0.25, 0.75, 0.75], "texture": "#2"},
				"down": {"uv": [0.25, 0.25, 0.75, 0.75], "texture": "#2"}
			}
		},
		{
			"name": "voxel",
			"from": [7.5, 12.89189, 7.48649],
			"to": [8.5, 13.89189, 8.48649],
			"rotation": {"angle": 0, "axis": "y", "origin": [8.5, 7.89189, 8.48649]},
			"faces": {
				"north": {"uv": [0.25, 0.25, 0.75, 0.75], "texture": "#2"},
				"east": {"uv": [0.25, 0.25, 0.75, 0.75], "texture": "#2"},
				"south": {"uv": [0.25, 0.25, 0.75, 0.75], "texture": "#2"},
				"west": {"uv": [0.25, 0.25, 0.75, 0.75], "texture": "#2"},
				"up": {"uv": [0.25, 0.25, 0.75, 0.75], "texture": "#2"},
				"down": {"uv": [0.25, 0.25, 0.75, 0.75], "texture": "#2"}
			}
		}
	],
	"display": {
		"thirdperson_righthand": {
			"rotation": [50, 0, 0],
			"scale": [0.7, 0.7, 0.7]
		},
		"thirdperson_lefthand": {
			"rotation": [50, 0, 0],
			"scale": [0.7, 0.7, 0.7]
		},
		"firstperson_righthand": {
			"translation": [2.25, 2.25, 0]
		},
		"firstperson_lefthand": {
			"translation": [2.25, 2.25, 0]
		},
		"ground": {
			"translation": [0, 3, 0]
		},
		"gui": {
			"rotation": [0, -20, -30],
			"translation": [0, 0.7, 0],
			"scale": [1.3, 1.3, 1.3]
		},
		"head": {
			"translation": [0, 12.5, 0]
		},
		"fixed": {
			"translation": [0, 0, -2.5]
		}
	}
}